django_multiple_auth-1.2.dist-info/DESCRIPTION.rst
django_multiple_auth-1.2.dist-info/METADATA
django_multiple_auth-1.2.dist-info/RECORD
django_multiple_auth-1.2.dist-info/WHEEL
django_multiple_auth-1.2.dist-info/metadata.json
django_multiple_auth-1.2.dist-info/top_level.txt
multiple_auth/__init__.py
multiple_auth/urls.py
multiple_auth/views.py
multiple_auth/templatetags/__init__.py
multiple_auth/templatetags/multiple_auth_tags.py
tests/__init__.py
tests/test_settings.py
tests/tests.py
tests/urls.py
