Metadata-Version: 2.0
Name: django-multiple-auth
Version: 1.2
Summary: Multiple login users at the same time
Home-page: https://github.com/EngageSports/django-multiple-auth
Author: Martyn CLEMENT
Author-email: martyn@engage-sports.com
License: UNKNOWN
Platform: UNKNOWN
Classifier: Environment :: Web Environment
Classifier: Framework :: Django
Classifier: Intended Audience :: Developers
Classifier: License :: OSI Approved :: BSD License
Classifier: Operating System :: OS Independent
Classifier: Programming Language :: Python
Classifier: Topic :: Software Development :: Libraries :: Python Modules
